gene/__init__.py
gene/cli.py
gene/config.py
gene/main.py
gene/query.py
gene/schemas.py
gene/utils.py
gene/database/__init__.py
gene/database/database.py
gene/database/dynamodb.py
gene/database/postgresql.py
gene/database/postgresql/add_fkeys.sql
gene/database/postgresql/add_indexes.sql
gene/database/postgresql/create_record_lookup_view.sql
gene/database/postgresql/create_tables.sql
gene/database/postgresql/delete_normalized_concepts.sql
gene/database/postgresql/drop_fkeys.sql
gene/database/postgresql/drop_indexes.sql
gene/etl/__init__.py
gene/etl/base.py
gene/etl/ensembl.py
gene/etl/exceptions.py
gene/etl/hgnc.py
gene/etl/merge.py
gene/etl/ncbi.py
gene/etl/update.py
gene_normalizer-0.11.1.dist-info/licenses/LICENSE
gene_normalizer-0.11.1.dist-info/METADATA
gene_normalizer-0.11.1.dist-info/WHEEL
gene_normalizer-0.11.1.dist-info/entry_points.txt
gene_normalizer-0.11.1.dist-info/top_level.txt
gene_normalizer-0.11.1.dist-info/RECORD
