Metadata-Version: 2.4
Name: gene-normalizer
Version: 0.11.1
Summary: VICC normalization routines for genes
Author: Alex Wagner, Kori Kuzma, James Stevenson
License-Expression: MIT
Project-URL: Homepage, https://github.com/cancervariants/gene-normalization
Project-URL: Documentation, https://gene-normalizer.readthedocs.io/en/latest/
Project-URL: Changelog, https://github.com/cancervariants/gene-normalization/releases
Project-URL: Source, https://github.com/cancervariants/gene-normalization
Project-URL: Bug Tracker, https://github.com/cancervariants/gene-normalization/issues
Classifier: Development Status :: 3 - Alpha
Classifier: Framework :: FastAPI
Classifier: Framework :: Pydantic
Classifier: Framework :: Pydantic :: 2
Classifier: Intended Audience :: Science/Research
Classifier: Intended Audience :: Developers
Classifier: Topic :: Scientific/Engineering :: Bio-Informatics
Classifier: Programming Language :: Python :: 3
Classifier: Programming Language :: Python :: 3.11
Classifier: Programming Language :: Python :: 3.12
Classifier: Programming Language :: Python :: 3.13
Requires-Python: >=3.11
License-File: LICENSE
Requires-Dist: pydantic==2.*
Requires-Dist: pydantic-settings
Requires-Dist: fastapi
Requires-Dist: uvicorn
Requires-Dist: click
Requires-Dist: boto3
Requires-Dist: ga4gh.vrs<3.0,>=2.2.0
Provides-Extra: pg
Requires-Dist: psycopg[binary]; extra == "pg"
Provides-Extra: etl
Requires-Dist: gffutils; extra == "etl"
Requires-Dist: biocommons.seqrepo; extra == "etl"
Requires-Dist: wags-tails~=0.4.0; extra == "etl"
Requires-Dist: setuptools; extra == "etl"
Provides-Extra: tests
Requires-Dist: pytest>=6.0; extra == "tests"
Requires-Dist: pytest-cov; extra == "tests"
Requires-Dist: mock; extra == "tests"
Requires-Dist: httpx; extra == "tests"
Requires-Dist: pyyaml; extra == "tests"
Requires-Dist: jsonschema; extra == "tests"
Requires-Dist: jsonschema~=4.24; extra == "tests"
Requires-Dist: deepdiff; extra == "tests"
Provides-Extra: dev
Requires-Dist: prek>=0.2.23; extra == "dev"
Requires-Dist: fastapi[standard]; extra == "dev"
Requires-Dist: ruff==0.14.10; extra == "dev"
Provides-Extra: docs
Requires-Dist: sphinx==6.1.3; extra == "docs"
Requires-Dist: sphinx-autodoc-typehints==1.22.0; extra == "docs"
Requires-Dist: sphinx-autobuild==2021.3.14; extra == "docs"
Requires-Dist: sphinx-copybutton==0.5.2; extra == "docs"
Requires-Dist: sphinxext-opengraph==0.8.2; extra == "docs"
Requires-Dist: furo==2023.3.27; extra == "docs"
Requires-Dist: gravis==0.1.0; extra == "docs"
Requires-Dist: sphinx-github-changelog==1.2.1; extra == "docs"
Requires-Dist: sphinx-click==5.0.1; extra == "docs"
Dynamic: license-file
